bbrest.py
ent_map.json
bbrest-0.5.0.dist-info/LICENSE
bbrest-0.5.0.dist-info/WHEEL
bbrest-0.5.0.dist-info/METADATA
bbrest-0.5.0.dist-info/RECORD
