Metadata-Version: 2.1
Name: bbrest
Version: 0.5.0
Summary: Blackboard REST API for Humans
Author: Matt Deakyne
Author-email: m.d@ku.edu
Requires-Python: >=3.6,<4.0
Classifier: Programming Language :: Python :: 3
Classifier: Programming Language :: Python :: 3.10
Classifier: Programming Language :: Python :: 3.6
Classifier: Programming Language :: Python :: 3.7
Classifier: Programming Language :: Python :: 3.8
Classifier: Programming Language :: Python :: 3.9
Requires-Dist: aiohttp
Requires-Dist: maya
Requires-Dist: requests
Requires-Dist: requests-html (>=0.10.0,<0.11.0)
Requires-Dist: selenium
